tetra_rp/__init__.py
tetra_rp/client.py
tetra_rp/config.py
tetra_rp/execute_class.py
tetra_rp/logger.py
tetra_rp/cli/__init__.py
tetra_rp/cli/main.py
tetra_rp/cli/commands/__init__.py
tetra_rp/cli/commands/apps.py
tetra_rp/cli/commands/build.py
tetra_rp/cli/commands/deploy.py
tetra_rp/cli/commands/init.py
tetra_rp/cli/commands/resource.py
tetra_rp/cli/commands/run.py
tetra_rp/cli/commands/test_mothership.py
tetra_rp/cli/commands/undeploy.py
tetra_rp/cli/commands/build_utils/__init__.py
tetra_rp/cli/commands/build_utils/handler_generator.py
tetra_rp/cli/commands/build_utils/lb_handler_generator.py
tetra_rp/cli/commands/build_utils/manifest.py
tetra_rp/cli/commands/build_utils/mothership_handler_generator.py
tetra_rp/cli/commands/build_utils/scanner.py
tetra_rp/cli/utils/__init__.py
tetra_rp/cli/utils/app.py
tetra_rp/cli/utils/conda.py
tetra_rp/cli/utils/deployment.py
tetra_rp/cli/utils/ignore.py
tetra_rp/cli/utils/skeleton.py
tetra_rp/cli/utils/skeleton_template/.env.example
tetra_rp/cli/utils/skeleton_template/.flashignore
tetra_rp/cli/utils/skeleton_template/.gitignore
tetra_rp/cli/utils/skeleton_template/README.md
tetra_rp/cli/utils/skeleton_template/main.py
tetra_rp/cli/utils/skeleton_template/mothership.py
tetra_rp/cli/utils/skeleton_template/pyproject.toml
tetra_rp/cli/utils/skeleton_template/requirements.txt
tetra_rp/cli/utils/skeleton_template/workers/__init__.py
tetra_rp/cli/utils/skeleton_template/workers/cpu/__init__.py
tetra_rp/cli/utils/skeleton_template/workers/cpu/endpoint.py
tetra_rp/cli/utils/skeleton_template/workers/gpu/__init__.py
tetra_rp/cli/utils/skeleton_template/workers/gpu/endpoint.py
tetra_rp/core/__init__.py
tetra_rp/core/deployment.py
tetra_rp/core/discovery.py
tetra_rp/core/exceptions.py
tetra_rp/core/validation.py
tetra_rp/core/api/__init__.py
tetra_rp/core/api/runpod.py
tetra_rp/core/resources/__init__.py
tetra_rp/core/resources/app.py
tetra_rp/core/resources/base.py
tetra_rp/core/resources/cloud.py
tetra_rp-0.24.0.dist-info/METADATA
tetra_rp-0.24.0.dist-info/WHEEL
tetra_rp-0.24.0.dist-info/entry_points.txt
tetra_rp-0.24.0.dist-info/top_level.txt
tetra_rp-0.24.0.dist-info/RECORD
