Metadata-Version: 2.4
Name: tetra_rp
Version: 0.24.0
Summary: A Python library for distributed inference and serving of machine learning models
Author-email: Marut Pandya <pandyamarut@gmail.com>, Patrick Rachford <prachford@icloud.com>, Dean Quinanola <dean.quinanola@runpod.io>
License: MIT
Classifier: Development Status :: 3 - Alpha
Classifier: Programming Language :: Python :: 3
Classifier: License :: OSI Approved :: MIT License
Classifier: Operating System :: OS Independent
Requires-Python: <3.15,>=3.10
Requires-Dist: cloudpickle>=3.1.1
Requires-Dist: runpod
Requires-Dist: python-dotenv>=1.0.0
Requires-Dist: pydantic>=2.0.0
Requires-Dist: rich>=14.0.0
Requires-Dist: typer>=0.12.0
Requires-Dist: questionary>=2.0.0
Requires-Dist: pathspec>=0.11.0
Requires-Dist: tomli>=2.0.0; python_version < "3.11"
